{
  "type": "minecraft:chest",
  "pools": [
    {
      "rolls": 10,
      "entries": [
        {
          "type": "minecraft:item",
          "name": "minecraft:dandelion",
          "weight": 5
        },
        {
          "type": "minecraft:item",
          "name": "minecraft:oxeye_daisy",
          "weight": 4
        },
        {
          "type": "minecraft:item",
          "name": "minecraft:cornflower",
          "weight": 4
        },
        {
          "type": "minecraft:item",
          "name": "minecraft:poppy",
          "weight": 3
        },
        {
          "type": "minecraft:item",
          "name": "minecraft:light_blue_wool",
          "weight": 3
        },
        {
          "type": "minecraft:item",
          "name": "minecraft:wheat",
          "weight": 4
        },
        {
          "type": "minecraft:item",
          "name": "minecraft:bread",
          "weight": 2
        },
        {
          "type": "minecraft:item",
          "name": "minecraft:hay_block",
          "weight": 3
        },
        {
          "type": "minecraft:item",
          "name": "minecraft:leather",
          "weight": 2
        },
        {
          "type": "minecraft:item",
          "name": "minecraft:shears",
          "weight": 1
        }
      ]
    }
  ]
}
